LICENSE
README.md
pyproject.toml
setup.py
sla_cli/__init__.py
sla_cli/entry.py
sla_cli.egg-info/PKG-INFO
sla_cli.egg-info/SOURCES.txt
sla_cli.egg-info/dependency_links.txt
sla_cli.egg-info/entry_points.txt
sla_cli.egg-info/requires.txt
sla_cli.egg-info/top_level.txt
sla_cli/db/db.json
sla_cli/src/__init__.py
sla_cli/src/cli/__init__.py
sla_cli/src/cli/context.py
sla_cli/src/cli/converters.py
sla_cli/src/cli/utils.py
sla_cli/src/cli/commands/__init__.py
sla_cli/src/cli/commands/download.py
sla_cli/src/cli/commands/ls.py
sla_cli/src/cli/commands/organise.py
sla_cli/src/common/__init__.py
sla_cli/src/common/console.py
sla_cli/src/common/path.py
sla_cli/src/common/regex.py
sla_cli/src/common/versioning.py
sla_cli/src/common/config/__init__.py
sla_cli/src/common/config/config.py
sla_cli/src/common/config/utils.py
sla_cli/src/common/config/validators.py
sla_cli/src/common/logger/__init__.py
sla_cli/src/common/logger/formatter.py
sla_cli/src/common/logger/init_logger.py
sla_cli/src/common/logger/logger_config.yml
sla_cli/src/db/__init__.py
sla_cli/src/db/schema.py
sla_cli/src/db/utils.py
sla_cli/src/db/accessors/__init__.py
sla_cli/src/db/accessors/abbreviations.py
sla_cli/src/db/accessors/base.py
sla_cli/src/db/accessors/datasets.py
sla_cli/src/db/accessors/factory.py
sla_cli/src/download/__init__.py
sla_cli/src/download/downloader.py
sla_cli/src/download/utils.py
sla_cli/src/download/isic/__init__.py
sla_cli/src/download/isic/download.py
sla_cli/src/download/isic/metadata.py
sla_cli/src/download/mednode/__init__.py
sla_cli/src/download/mednode/download.py
sla_cli/src/download/pad_ufes_20/__init__.py
sla_cli/src/download/pad_ufes_20/download.py
sla_cli/src/download/ph2/__init__.py
sla_cli/src/download/ph2/download.py
sla_cli/tests/__init__.py
sla_cli/tests/conftest.py
sla_cli/tests/test_cli.py
sla_cli/tests/src/__init__.py
sla_cli/tests/src/cli/__init__.py
sla_cli/tests/src/cli/test_converters.py
sla_cli/tests/src/cli/commands/__init__.py
sla_cli/tests/src/cli/commands/download/__init__.py
sla_cli/tests/src/cli/commands/download/test_download.py
sla_cli/tests/src/cli/commands/ls/__init__.py
sla_cli/tests/src/cli/commands/ls/conftest.py
