Metadata-Version: 2.1
Name: sla-cli
Version: 0.2.1
Summary: A CLI tool designed to help source data for skin lesion research.
Home-page: https://github.com/DavidWalshe93/SL-CLI
Author: David Walshe
Author-email: david.walshe93@gmail.com
License: MIT
Project-URL: Homepage, https://github.com/DavidWalshe93/SL-CLI
Project-URL: Bug Tracker, https://github.com/DavidWalshe93/SL-CLI/issues
Keywords: cancer-research,cancer,skin-lesion,skin,lesion,melanoma,datasets,data,data-acquisition,research,skin-cancer,utility,tool,academic,download,downloader,isic,MEDNODE,DermIS,DermQuest,PAD-UFES-20,MClass,Atlas-of-Dermascopy,HAM10000,BCN20000,DERMOFIT,cli,command-line-tool
Platform: UNKNOWN
Classifier: Development Status :: 3 - Alpha
Classifier: Intended Audience :: Healthcare Industry
Classifier: Intended Audience :: Developers
Classifier: Intended Audience :: Science/Research
Classifier: Environment :: Console
Classifier: Natural Language :: English
Classifier: License :: OSI Approved :: MIT License
Classifier: Programming Language :: Python :: 3.7
Classifier: Programming Language :: Python :: 3.8
Classifier: Programming Language :: Python :: 3.9
Classifier: Operating System :: OS Independent
Requires-Python: >=3.6
